LICENSE
MANIFEST.in
README.md
setup.py
tox.ini
passivetotal2/__init__.py
passivetotal2/__init___BACKUP_65253.py
passivetotal2/__init___BACKUP_65849.py
passivetotal2/__init___BASE_65253.py
passivetotal2/__init___BASE_65849.py
passivetotal2/__init___LOCAL_65253.py
passivetotal2/__init___LOCAL_65849.py
passivetotal2/__init___REMOTE_65253.py
passivetotal2/__init___REMOTE_65849.py
passivetotal2/dns.py
passivetotal2/output.py
passivetotal2/response.py
passivetotal2/userinput.py
passivetotal2/util.py
passivetotal2.egg-info/PKG-INFO
passivetotal2.egg-info/SOURCES.txt
passivetotal2.egg-info/dependency_links.txt
passivetotal2.egg-info/entry_points.txt
passivetotal2.egg-info/requires.txt
passivetotal2.egg-info/top_level.txt
passivetotal2/cli/__init__.py
passivetotal2/cli/account.py
passivetotal2/cli/actions.py
passivetotal2/cli/artifact.py
passivetotal2/cli/dns.py
passivetotal2/cli/enrich.py
passivetotal2/cli/host.py
passivetotal2/cli/monitor.py
passivetotal2/cli/project.py
passivetotal2/cli/setup.py
passivetotal2/cli/ssl.py
passivetotal2/cli/trackers.py
passivetotal2/cli/whois.py
passivetotal2/client/__init__.py
passivetotal2/client/account.py
passivetotal2/client/actions.py
passivetotal2/client/artifact.py
passivetotal2/client/baseclient.py
passivetotal2/client/dns.py
passivetotal2/client/enrichment.py
passivetotal2/client/host.py
passivetotal2/client/project.py
passivetotal2/client/ssl.py
passivetotal2/client/whois.py