Metadata-Version: 1.1
Name: passivetotal2
Version: 1.0.3
Summary: PassiveTotal client, version 2
Home-page: https://www.bitbucket.org/riskiq/passivetotal_client
Author: Johan Nestaas, Nate Falke
Author-email: johan.nestaas@riskiq.net, nate.falke@riskiq.net
License: Copyright RiskIQ
Platform: UNKNOWN
Classifier: Development Status :: 5 - Production/Stable
Classifier: Environment :: Console
Classifier: Environment :: X11 Applications :: Qt
Classifier: Environment :: MacOS X
Classifier: Environment :: Win32 (MS Windows)
Classifier: Operating System :: POSIX
Classifier: Operating System :: MacOS :: MacOS X
Classifier: Operating System :: Microsoft :: Windows
Classifier: Programming Language :: Python
